mp4mdl/__init__.py
mp4mdl/mp4mdl.py
mp4mdl/download/__init__.py
mp4mdl/download/mp4_downloader.py
mp4mdl/download/segment_downloader.py
mp4mdl/lecteur/__init__.py
mp4mdl/lecteur/oneupload.py
mp4mdl/lecteur/sendvid.py
mp4mdl/lecteur/sibnet.py
mp4mdl/lecteur/vidmoly.py
mp4mdl/scrap/__init__.py
mp4mdl/scrap/get_best_qualite_url.py
mp4mdl/scrap/get_m3u8_url.py
mp4mdl/scrap/get_mp4_url.py
mp4mdl-0.1.6.dist-info/METADATA
mp4mdl-0.1.6.dist-info/WHEEL
mp4mdl-0.1.6.dist-info/entry_points.txt
mp4mdl-0.1.6.dist-info/top_level.txt
mp4mdl-0.1.6.dist-info/RECORD
