Metadata-Version: 2.1
Name: mp4mdl
Version: 0.1.6
Summary: Un outil pour télécharger et gérer des vidéos MP4
Home-page: https://git.maddoxserv.com/maddox/MP4MDL
Author: Maddox
Author-email: maddoxtes@gmail.com
Classifier: Programming Language :: Python :: 3
Classifier: License :: OSI Approved :: MIT License
Classifier: Operating System :: OS Independent
Requires-Python: >=3.6
Requires-Dist: requests
Requires-Dist: urllib3
Requires-Dist: beautifulsoup4
Requires-Dist: ffmpeg-python
